[1,["3fwDvYXQ1LbLYaz1EL3/kA@f9941","b0MXXWTL9FWZLqh4NrrFsq@f9941","0e41W3jvlDGobY3md4NNQd@f9941","0e41W3jvlDGobY3md4NNQd@6c48a","12ZhBgeXdNm4PWp5JScSfL@6c48a","1ei+7kV6xGQ70gK1PCMeLh@6c48a","22oADobHJAE6Z+CEOo4qst@6c48a","25gn7p+9FDPpKtKNfXYdWr@6c48a","12ZhBgeXdNm4PWp5JScSfL@f9941","83HqfgqfhBpIQGhqsNMVVU@f9941","25gn7p+9FDPpKtKNfXYdWr@f9941","db7o52A/1M/6Q+c3+KEeTB@f9941","76KU7ukExGOo9JxscwNU2j@f9941","1ei+7kV6xGQ70gK1PCMeLh@f9941","22oADobHJAE6Z+CEOo4qst@f9941","efvsOzRfJNYapmi1D4MJOD@f9941","c9hLR1fRVAGanvSI7TNUGD@f9941","edC9sqm/pKtKkqW3moQiJF@f9941","45j2FUQCRDN67qMb5Glt0t@f9941","d8k8LTbMpL4KIqkI5d9I1K@f9941","4aRkCzkJpC7qwFO3K9ZYqv@f9941","3fwDvYXQ1LbLYaz1EL3/kA@6c48a","4aRkCzkJpC7qwFO3K9ZYqv@6c48a","76KU7ukExGOo9JxscwNU2j@6c48a","83HqfgqfhBpIQGhqsNMVVU@6c48a","c9hLR1fRVAGanvSI7TNUGD@6c48a","d8k8LTbMpL4KIqkI5d9I1K@6c48a","db7o52A/1M/6Q+c3+KEeTB@6c48a","edC9sqm/pKtKkqW3moQiJF@6c48a","efvsOzRfJNYapmi1D4MJOD@6c48a"],["node","_spriteFrame","_textureSource","_parent","root","nodeNoOrder","btnReturn","shopItemContainer","starContainer","lbCurrentTime","data"],["cc.SpriteFrame",["cc.Label",["_string","_actualFontSize","_fontSize","_lineHeight","_enableOutline","_outlineWidth","_overflow","_horizontalAlign","node","__prefab","_color","_outlineColor"],-5,1,4,5,5],["cc.Node",["_name","_layer","_components","_prefab","_parent","_children","_lpos","_lscale"],1,9,4,1,2,5,5],["cc.UITransform",["node","__prefab","_contentSize","_anchorPoint"],3,1,4,5,5],["cc.Sprite",["_sizeMode","_type","node","__prefab","_spriteFrame","_color"],1,1,4,6,5],["cc.Prefab",["_name"],2],["cc.Node",["_name","_layer","_parent","_components","_prefab","_lpos"],1,1,12,4,5],["cc.CompPrefabInfo",["fileId"],2],["cc.Widget",["_alignFlags","_originalWidth","_originalHeight","node","__prefab"],0,1,4],["cc.Mask",["node","__prefab"],3,1,4],["cc.Graphics",["node","__prefab","_fillColor"],3,1,4,5],["cc.BlockInputEvents",["node","__prefab"],3,1,4],["310c5VWifJKybbNLEmyY8EM",["node","__prefab","lbCurrentTime","starContainer","shopItemContainer","btnReturn","nodeNoOrder"],3,1,4,1,1,1,1,1],["cc.PrefabInfo",["fileId","instance","targetOverrides","nestedPrefabInstanceRoots","root","asset"],-1,1,1],["cc.Layout",["_resizeMode","_layoutType","_spacingX","_isAlign","node","__prefab"],-1,1,4],["cc.Button",["_transition","_zoomScale","node","__prefab"],1,1,4],["cc.ScrollView",["bounceDuration","brake","elastic","vertical","node","__prefab","_content"],-1,1,4,1]],[[7,0,2],[13,0,1,2,3,4,5,5],[3,0,1,2,1],[2,0,1,4,2,3,6,3],[4,2,3,4,1],[2,0,1,4,2,3,3],[3,0,1,2,3,1],[2,0,1,4,5,2,3,6,3],[2,0,1,4,2,3,6,7,3],[3,0,1,1],[15,0,1,2,3,3],[4,0,2,3,5,4,2],[1,0,1,3,8,9,4],[1,0,1,2,4,5,8,9,10,11,6],[8,0,1,2,3,4,4],[1,0,1,2,4,8,9,11,5],[2,0,1,5,2,3,3],[9,0,1,1],[10,0,1,2,1],[14,0,1,2,3,4,5,5],[5,0,2],[2,0,1,5,2,3,6,3],[2,0,1,4,5,2,3,3],[6,0,1,2,3,4,5,3],[11,0,1,1],[12,0,1,2,3,4,5,6,1],[4,1,0,2,3,4,3],[16,0,1,2,3,4,5,6,5],[1,0,1,4,5,8,9,10,11,5],[1,0,1,2,3,8,9,10,5],[1,0,7,1,2,6,8,9,10,6],[1,0,1,2,3,4,5,8,9,10,7],[1,0,1,2,3,6,8,9,10,6],[1,0,7,1,2,3,6,8,9,10,7]],[[[{"name":"图层 82 拷贝 2","rect":{"x":0,"y":0,"width":185,"height":80},"offset":{"x":0,"y":0},"originalSize":{"width":185,"height":80},"rotated":false,"capInsets":[0,0,0,0],"vertices":{"rawPosition":[-92.5,-40,0,92.5,-40,0,-92.5,40,0,92.5,40,0],"indexes":[0,1,2,2,1,3],"uv":[0,80,185,80,0,0,185,0],"nuv":[0,0,1,0,0,1,1,1],"minPos":{"x":-92.5,"y":-40,"z":0},"maxPos":{"x":92.5,"y":40,"z":0}},"packable":true,"pixelsToUnit":100,"pivot":{"x":0.5,"y":0.5},"meshType":0}],[0],0,[0],[2],[3]],[[{"name":"ea30b051fb26d4621e83bdb5efff8d955c594bb91e25-BmKubk 拷贝","rect":{"x":1,"y":1,"width":1543,"height":924},"offset":{"x":0,"y":0},"originalSize":{"width":1545,"height":926},"rotated":false,"capInsets":[383,0,703,0],"vertices":{"rawPosition":[-771.5,-462,0,771.5,-462,0,-771.5,462,0,771.5,462,0],"indexes":[0,1,2,2,1,3],"uv":[1,925,1544,925,1,1,1544,1],"nuv":[0.0006472491909385113,0.0010799136069114472,0.9993527508090615,0.0010799136069114472,0.0006472491909385113,0.9989200863930886,0.9993527508090615,0.9989200863930886],"minPos":{"x":-771.5,"y":-462,"z":0},"maxPos":{"x":771.5,"y":462,"z":0}},"packable":true,"pixelsToUnit":100,"pivot":{"x":0.5,"y":0.5},"meshType":0}],[0],0,[0],[2],[4]],[[{"name":"包租婆","rect":{"x":0,"y":0,"width":119,"height":119},"offset":{"x":0,"y":0},"originalSize":{"width":119,"height":119},"rotated":false,"capInsets":[0,0,0,0],"vertices":{"rawPosition":[-59.5,-59.5,0,59.5,-59.5,0,-59.5,59.5,0,59.5,59.5,0],"indexes":[0,1,2,2,1,3],"uv":[0,119,119,119,0,0,119,0],"nuv":[0,0,1,0,0,1,1,1],"minPos":{"x":-59.5,"y":-59.5,"z":0},"maxPos":{"x":59.5,"y":59.5,"z":0}},"packable":true,"pixelsToUnit":100,"pivot":{"x":0.5,"y":0.5},"meshType":0}],[0],0,[0],[2],[5]],[[{"name":"学生","rect":{"x":0,"y":0,"width":119,"height":119},"offset":{"x":0,"y":0},"originalSize":{"width":119,"height":119},"rotated":false,"capInsets":[0,0,0,0],"vertices":{"rawPosition":[-59.5,-59.5,0,59.5,-59.5,0,-59.5,59.5,0,59.5,59.5,0],"indexes":[0,1,2,2,1,3],"uv":[0,119,119,119,0,0,119,0],"nuv":[0,0,1,0,0,1,1,1],"minPos":{"x":-59.5,"y":-59.5,"z":0},"maxPos":{"x":59.5,"y":59.5,"z":0}},"packable":true,"pixelsToUnit":100,"pivot":{"x":0.5,"y":0.5},"meshType":0}],[0],0,[0],[2],[6]],[[{"name":"上班族","rect":{"x":0,"y":0,"width":119,"height":119},"offset":{"x":0,"y":0},"originalSize":{"width":119,"height":119},"rotated":false,"capInsets":[0,0,0,0],"vertices":{"rawPosition":[-59.5,-59.5,0,59.5,-59.5,0,-59.5,59.5,0,59.5,59.5,0],"indexes":[0,1,2,2,1,3],"uv":[0,119,119,119,0,0,119,0],"nuv":[0,0,1,0,0,1,1,1],"minPos":{"x":-59.5,"y":-59.5,"z":0},"maxPos":{"x":59.5,"y":59.5,"z":0}},"packable":true,"pixelsToUnit":100,"pivot":{"x":0.5,"y":0.5},"meshType":0}],[0],0,[0],[2],[7]],[[[20,"KLM_TakeoutPanel"],[16,"KLM_TakeoutPanel",33554432,[-13,-14,-15,-16,-17,-18,-19,-20,-21],[[2,-2,[0,"556iBRLBZMN5FSurNNen0R"],[5,2340,1080]],[14,45,4680,100,-3,[0,"2caphlGrJNUqmSxIok2F0v"]],[17,-4,[0,"34NuBB8RZKi5rRtCf4rzj5"]],[18,-5,[0,"e9A33ffotC66NEP27wu/lo"],[4,16777215]],[24,-6,[0,"7d9DZaBTVJSIVC5Tt5gOZ+"]],[25,-12,[0,"1bdmDJEXdKCKPG2H0x47KY"],-11,-10,-9,-8,-7]],[1,"06CmpYjhdP65VQCS11jX1Q",null,null,null,-1,0]],[21,"takeoutItem",33554432,[-23,-24,-25,-26,-27,-28,-29,-30,-31,-32,-33,-34,-35,-36,-37,-38,-39,-40,-41,-42],[[2,-22,[0,"f4FD8NLmdEyYcL33Yd0rx9"],[5,467,586]]],[1,"24GQMMhghJp5/86TsEAjgA",null,null,null,1,0],[1,233.5,0,0]],[7,"starContainer",33554432,1,[-45,-46,-47,-48,-49],[[6,-43,[0,"4fUV28hKZKLLe1/e8bdiZK"],[5,358.4,100],[0,0,0.5]],[19,1,1,-35.4,true,-44,[0,"eflxBlMFtDV5CICJ8CAsnS"]]],[1,"deRAxeStZIq47wC2JtDHzJ",null,null,null,1,0],[1,-601.401,269.278,0]],[22,"spAvatar",33554432,2,[-51,-52,-53,-54,-55,-56,-57],[[9,-50,[0,"bfbMeaik1IWrsKi81A/hc6"]]],[1,"38Vahd+j1A9ID2lbNfpaTs",null,null,null,1,0]],[16,"view",33554432,[-62],[[2,-58,[0,"1aRi/+UuxILoL6nLM6XQPh"],[5,1640.888,653.1640000000001]],[17,-59,[0,"1drIKhwZBI6K07ea+oUOod"]],[18,-60,[0,"2e0le125hFPLj81OWqIiaD"],[4,16777215]],[14,45,240,250,-61,[0,"86qTVo+exPyrmMw8qgFH4C"]]],[1,"5cUHYJ7Q1D9YdUSuLojmVU",null,null,null,1,0]],[7,"shopItemContainer",33554432,5,[2],[[6,-63,[0,"cbRj/gVnJLIoL/9FvMHR78"],[5,467,652.3980000000001],[0,0,0.5]],[19,1,1,16.8,true,-64,[0,"c07w2s+iVLgJyJsn+5/bko"]]],[1,"af18usMxFKFqLSW+vxOvUz",null,null,null,1,0],[1,-820.4440000000001,2.1935000000000002,0]],[7,"btnVideo",33554432,2,[-67,-68,-69],[[2,-65,[0,"5cpHpBlhRN06hGyWXlvZ/A"],[5,185,80]],[10,3,0.9,-66,[0,"c6lYMdTZJBIo+wxBDFZg11"]]],[1,"74QeA3ox1L3qHvhK3Qu7Ue",null,null,null,1,0],[1,-111.329,-220.855,0]],[7,"btnAccept",33554432,2,[-72,-73],[[2,-70,[0,"bePLMBbNFLx65QJ/5Zt9+0"],[5,185,80]],[10,3,0.9,-71,[0,"7aVBECfzxCk6uwvo6ZoKpX"]]],[1,"86VG7i+m9Lu6/cy0UAZl7c",null,null,null,1,0],[1,-111.329,-220.855,0]],[7,"btnRefuse",33554432,2,[-76,-77],[[2,-74,[0,"c0sWOcwQRDJ4PzPO5XgD2o"],[5,185,80]],[10,3,0.9,-75,[0,"55EYxZxt1M5oJ0TI49aCe2"]]],[1,"13TUsHNiZAMLJO3SWs4VgA",null,null,null,1,0],[1,110.786,-219.475,0]],[7,"btnReturn",33554432,1,[-80],[[2,-78,[0,"9aPrIZSo9GPafnCSQ0PjEd"],[5,100,99]],[10,3,0.9,-79,[0,"c73L7At7NAF7l+9GLhi/kM"]]],[1,"15ANwp3ZtNEIeHbb2wvX/O",null,null,null,1,0],[1,-853.43,0.13,0]],[5,"DAH_Mask",33554432,1,[[2,-81,[0,"31MfGn38xCiILkGlG345ln"],[5,2340,1080]],[11,0,-82,[0,"9cs165MJRBlobL+UCnvDHg"],[4,3003121664],0],[14,45,2,2,-83,[0,"72IGUyS85GUIbuLk5Ewvhv"]]],[1,"4b7oEy0TZE/5TZx/OkK22y",null,null,null,1,0]],[7,"ScrollView",33554432,1,[5],[[2,-84,[0,"70645iMd9ClYpB4ui+ItyQ"],[5,1640.888,653.1640000000001]],[27,0.23,0.75,false,false,-85,[0,"b0Z9C/NoVMGZ/+UfhR7yT+"],6]],[1,"c4MdwVTD1INaiw+yNAIuFN",null,null,null,1,0],[1,34.527000000000044,-123.19399999999996,0]],[3,"NodeNoOrder",33554432,1,[[2,-86,[0,"19cI2sUhZDirIC083lO6vx"],[5,196.33984375,53.4]],[28,"暂 无 订 单",40,true,1.5,-87,[0,"d3ERrrLK9B17ghv1Qo0bEO"],[4,4287924836],[4,4288252480]]],[1,"dd5tZLQUZHHZbaDixyLgSE",null,null,null,1,0],[1,14.301,-73.285,0]],[3,"bg",33554432,1,[[2,-88,[0,"95aC4sR1VKYqF/pfUFC3TW"],[5,1871.8259999999998,988.784]],[26,1,0,-89,[0,"edcF1alJNKHLvsPlRosS4T"],1]],[1,"eedH1inmhOzpXO8/B9kPxe",null,null,null,1,0],[1,-8.753999999999905,-8.047000000000025,0]],[3,"Score",33554432,1,[[2,-90,[0,"b7UBCMxzdMYJo4tRgt+I42"],[5,200,75.6]],[12,"店铺评分：",40,60,-91,[0,"e5qmG5mXFC577GSGoyFNBt"]]],[1,"1eYc80DdRLj4IG3IbnbYIj",null,null,null,1,0],[1,-681.964,264.384,0]],[8,"星星",33554432,3,[[9,-92,[0,"f5+acZjtdGK5wTPhsHqwU0"]],[4,-93,[0,"f8QOl4oMlEv7qRHvSerAhv"],2]],[1,"bacznzuchAMpX1TqimWxA3",null,null,null,1,0],[1,50,0,0],[1,0.6,0.6,1]],[8,"星星-001",33554432,3,[[9,-94,[0,"d3XzJcxb1N8KUWnVBX8NKi"]],[4,-95,[0,"3d6cHXoJBHKqFsFi00BmzY"],3]],[1,"85J5S6y/ZFVKSMNAaCyHER",null,null,null,1,0],[1,114.6,0,0],[1,0.6,0.6,1]],[8,"星星-002",33554432,3,[[9,-96,[0,"b9wMhivnNOcKsjTfkLsxhG"]],[4,-97,[0,"bc6F8q56hJrZCk4Xl809j9"],4]],[1,"d5jbIUUr1O7Z18oJwvdE1f",null,null,null,1,0],[1,179.2,0,0],[1,0.6,0.6,1]],[8,"星星-003",33554432,3,[[9,-98,[0,"7ewaSG1QBDm62wYANde+LE"]],[4,-99,[0,"0cq7k4cnpAOo/QKRteEti2"],5]],[1,"adiZKdbvZBn6h2U4TNhceq",null,null,null,1,0],[1,243.79999999999998,0,0],[1,0.6,0.6,1]],[8,"星星-004",33554432,3,[[9,-100,[0,"eewQIjWVVHRILMWQ5E6yfT"]],[4,-101,[0,"f0v6gYKclIbYAEgoejw4Ve"],6]],[1,"72Ke2Zg/tCKa/i/l18PEXz",null,null,null,1,0],[1,308.4,0,0],[1,0.6,0.6,1]],[3,"lblTitle",33554432,1,[[6,-102,[0,"916m3ge1JIMIbFicvcz9UU"],[5,200,75.6],[0,0,0.5]],[12,"小小冷面摊",40,60,-103,[0,"ddCbLLaL9NwYMIu21+q4XE"]]],[1,"ab2PuheyBD55z0FibMoF0l",null,null,null,1,0],[1,-773.386,378.044,0]],[23,"lblTime",33554432,1,[[[2,-104,[0,"7cn3EKbxlL/KIGPkYoh9kI"],[5,100.09765625,75.6]],-105],4,1],[1,"c1MEogHMBK0a23C/97jGQk",null,null,null,1,0],[1,0,378.044,0]],[5,"bg",33554432,2,[[2,-106,[0,"9b67ZXfV1K77bk+ei7/9cI"],[5,467,586]],[4,-107,[0,"e4p7B/HK5H/remBklH8BB/"],7]],[1,"b8fCpfWtlIR68+0leaRI+s",null,null,null,1,0]],[3,"bg-001",33554432,2,[[2,-108,[0,"e2xloc8l9FBKGazt2KXOvn"],[5,442.866,563.1370000000001]],[11,0,-109,[0,"11CgN7Cy9OioeBx01zH+HQ"],[4,4284766802],8]],[1,"71vPCXXmhHJK5Kg1aoLW08",null,null,null,1,0],[1,-0.635,0.14949999999999974,0]],[3,"DAH_Mask",33554432,2,[[2,-110,[0,"b0eyJPUX1DNKTa5FM5te1Z"],[5,416.52799999999996,146.13500000000002]],[11,0,-111,[0,"10M7Ms0/dE16dReeksbWnm"],[4,4294758574],9]],[1,"25uzceIylGia2RhpLbA5QF",null,null,null,1,0],[1,0.4199999999999968,68.0855,0]],[3,"DAH_Mask-001",33554432,2,[[2,-112,[0,"fcjKshFnZM3rKKLqCZ/vGn"],[5,416.52799999999996,131.484]],[11,0,-113,[0,"a01Bc6/RtPEJc9Z9XkZ115"],[4,4294949802],10]],[1,"66QP84MC5Fd4cDC1gzIEtl",null,null,null,1,0],[1,0.42000000000007276,-85.87650000000002,0]],[3,"上班族",33554432,4,[[2,-114,[0,"245wxB+r9Kd6YfYWvKJuCp"],[5,119,119]],[4,-115,[0,"f4rBax0s1FzZNVKHueu2YX"],11]],[1,"c2+ktozMtAga8zrK4H/G/R",null,null,null,1,0],[1,-139.63,212.13,0]],[3,"体育",33554432,4,[[2,-116,[0,"4fAHvaC3ZCjaBgICVGfNvb"],[5,119,119]],[4,-117,[0,"e2JkfR2dNJT5ZPvN6QEt6L"],12]],[1,"6dsgDZvaBMFIGzmSCO0YKZ",null,null,null,1,0],[1,-139.63,212.13,0]],[3,"便衣",33554432,4,[[2,-118,[0,"d8EAxGTixGRZXO0y6TuclA"],[5,119,119]],[4,-119,[0,"b38Xgya6FFT5+0RIlXNHI6"],13]],[1,"efrmV0UwZF1rML1WtWdDvJ",null,null,null,1,0],[1,-139.63,212.13,0]],[3,"包租婆",33554432,4,[[2,-120,[0,"9aCIvvBA1B/ZGh8Ba13BGR"],[5,119,119]],[4,-121,[0,"6aF9Y1XSdHmqHvpwx7FyHJ"],14]],[1,"37xhymhSJM3o/QMEL0aFND",null,null,null,1,0],[1,-139.63,212.13,0]],[3,"学生",33554432,4,[[2,-122,[0,"f1mhoDIRdOv5Zgj9D8WF1n"],[5,119,119]],[4,-123,[0,"40AENvDIBHWpr1BMgZjZee"],15]],[1,"68SrHQwrJAQ7vhrwIVJd/S",null,null,null,1,0],[1,-139.63,212.13,0]],[3,"美女",33554432,4,[[2,-124,[0,"92ob/DgE1P3oytSMNJVVOK"],[5,119,119]],[4,-125,[0,"2fbBeT8SBBpZReYKKb5J0A"],16]],[1,"acF7VG7z1Egqq4BPO6mU6n",null,null,null,1,0],[1,-139.63,212.13,0]],[3,"非主流",33554432,4,[[2,-126,[0,"b3SviH2WBAvaMy8K1UXMhu"],[5,119,119]],[4,-127,[0,"f50bM9xV9KF5KhLd1cyrw/"],17]],[1,"2e9aNNZvhD67uP8384zXIG",null,null,null,1,0],[1,-139.63,212.13,0]],[3,"lblName",33554432,2,[[6,-128,[0,"c6+tcFfARJlZ/v9n6C4jmv"],[5,120,75.6],[0,0,0.5]],[12,"非主流",40,60,-129,[0,"38HSBuIgBDzLlTv3sMV3GL"]]],[1,"1bOsl5EWJOUrZNuw3F0Jqe",null,null,null,1,0],[1,-67.402,231.045,0]],[3,"nodeNew",33554432,2,[[2,-130,[0,"0935IYeGJEKJ0BLqVkReDO"],[5,84,99]],[4,-131,[0,"dbfvR7sRJJjaLM8YNH7ppl"],18]],[1,"b8tzuT8G9CRJDnCr9DgNJg",null,null,null,1,0],[1,-191.615,272.505,0]],[3,"lblExpirationTime",33554432,2,[[6,-132,[0,"792Q+/pRlLwKwLAVz7v4y+"],[5,262.58544921875,75.6],[0,0,0.5]],[29,"过期时间：14:00",35,35,60,-133,[0,"277jaagkBMDKD4EjUhlnTz"],[4,4285071298]]],[1,"f4ek98ZCVMCrj/g3wvQRj8",null,null,null,1,0],[1,-67.402,171.452,0]],[3,"lblContent",33554432,2,[[6,-134,[0,"73odU7YClG5Igg4T30b0JN"],[5,374.074,90.39999999999999],[0,0,1]],[30,"送个辣条煎饼过来吧送个辣条煎饼过来吧",0,30,30,3,-135,[0,"67Yi9QQWZKPoXoPj8WPZ+N"],[4,4279440147]]],[1,"40HHkYzCBCTqthrDnQpeXY",null,null,null,1,0],[1,-188.236,148.092,0]],[8,"钱",33554432,2,[[2,-136,[0,"059FThP21Pdb31FYSpxC4W"],[5,132,93]],[4,-137,[0,"8cqz5rXuJJObgV/qyn41H7"],19]],[1,"4a7OOdniJLFqJYrDW9aUo1",null,null,null,1,0],[1,84.622,24.729,0],[1,0.6,0.6,1]],[3,"lblPrice",33554432,2,[[6,-138,[0,"33bElvmH9Kd7H/dhb1fiSK"],[5,44.9306640625,81.6],[0,0,0.5]],[31,"25",35,35,60,true,3,-139,[0,"a3j/g6WupMcLFC1S6k9vbo"],[4,4281925551]]],[1,"a3LVHJy/5Oc7PUeiklwnVD",null,null,null,1,0],[1,133.723,21.01,0]],[3,"lblNote",33554432,2,[[6,-140,[0,"e9D+JdQNpONYd964Y9iwQH"],[5,374.074,127.8],[0,0.5,1]],[32,"备注：倒不是我自己想吃备注：倒不是我自己想吃倒不是我自己想吃倒不是我自己想吃倒不是我自己想吃",26,26,30,3,-141,[0,"bdFdsnl7dM9bOJmA7GTJlq"],[4,4281679701]]],[1,"6eomjD9sNLIq7k5pYNmMZs",null,null,null,1,0],[1,0,-19.144,0]],[3,"lblMissing",33554432,2,[[6,-142,[0,"c2d+HDLmNNBKcZeZBINfZm"],[5,374.074,75.6],[0,0,0.5]],[33,"缺货：${}",0,26,26,60,3,-143,[0,"4brV18hKBI+4qU1Us6XQ6/"],[4,4282335206]]],[1,"daXnBSpPpHYpGjsgRvgjMm",null,null,null,1,0],[1,-190.184,17.534,0]],[5,"图层 82 拷贝 4",33554432,8,[[2,-144,[0,"8eeEceMqpI6ol2fZegKK73"],[5,185,80]],[4,-145,[0,"91vG2HYbBFypWy6RvQMMBD"],20]],[1,"85J2I3ukpD84vs46+ckqGY",null,null,null,1,0]],[5,"Label",33554432,8,[[2,-146,[0,"2eVzFWsEZIuLYiTQ09UW70"],[5,72,54.4]],[15,"接单",34,34,true,-147,[0,"89AjKpd8VMPK9Mno0yJVZr"],[4,4280110192]]],[1,"42OEOBZBZFG4lpLwvyw6Be",null,null,null,1,0]],[5,"图层 82 拷贝 4",33554432,7,[[2,-148,[0,"5e7nXtHfNP+IoyhnesCgQj"],[5,185,80]],[4,-149,[0,"58FdU4ugxLZYjr/E17jqdR"],21]],[1,"fcpmGPpx1IcrnPPqwIBspc",null,null,null,1,0]],[8,"广告",33554432,7,[[2,-150,[0,"7eQ01iX2dH3I0Fc/iGUCFx"],[5,61,62]],[4,-151,[0,"e1JPN5g4hEgoueayAWF//7"],22]],[1,"18+LK63DVObIAzrPE9gjJO",null,null,null,1,0],[1,-74.705,32.372,0],[1,0.7,0.7,1]],[5,"Label",33554432,7,[[2,-152,[0,"e4pSvL1yVK6bImSOOLrM1f"],[5,72,54.4]],[15,"进货",34,34,true,-153,[0,"bdTRlyGj9IPodW8HUF6vz5"],[4,4280110192]]],[1,"e9bl+ZJ0FO04UhGRPQjjE2",null,null,null,1,0]],[5,"btnRefuse-001",33554432,9,[[2,-154,[0,"33cgC+eDdHKr/Gqrg3uu9L"],[5,185,80]],[4,-155,[0,"4bvjSsiX5OGqkpdhBMIL4J"],23]],[1,"71cx7r5hVJIZ6l+EdQlUw2",null,null,null,1,0]],[5,"Label",33554432,9,[[2,-156,[0,"e9sVpqXQ9E6ZBqFnbLRQqz"],[5,72,54.4]],[15,"拒单",34,34,true,-157,[0,"cbkT5eAblIkKClH1tgt9M6"],[4,4281220969]]],[1,"f7pqkxOxVAGo7lgeKgSAs0",null,null,null,1,0]],[3,"NodeTimeout",33554432,2,[[2,-158,[0,"83gtfkEJJJO7B8NsycIh64"],[5,122.892578125,52.4]],[13,"已 超 时",34,34,true,1,-159,[0,"a7ClhgWShGrZIddJhk1jxS"],[4,4285295847],[4,4281479874]]],[1,"003TQ9VsxJIpSyzzrdauvi",null,null,null,1,0],[1,-3.36,-224.082,0]],[3,"NodeCookEnd",33554432,2,[[2,-160,[0,"8dRjSqCkJGCoOXuqKB0lhb"],[5,166.3388671875,52.4]],[13,"制 作 完 成",34,34,true,1,-161,[0,"b6pWxjinxJvKOcoOJUSKP+"],[4,4282368767],[4,4280502698]]],[1,"fdgD6NknhH2LMkVibWSfQd",null,null,null,1,0],[1,-3.811,-224.082,0]],[3,"NodeDelivered",33554432,2,[[2,-162,[0,"5erLSrfWlHuLcxodu/aUVe"],[5,122.892578125,52.4]],[13,"已 送 达",34,34,true,1,-163,[0,"27lyuyIjNCMICkgHu7YN0w"],[4,4284540015],[4,4281169197]]],[1,"2buOhypDVN/adtcbYu8lho",null,null,null,1,0],[1,-3.811,-224.082,0]],[3,"NodeRefused",33554432,2,[[2,-164,[0,"dfkM9bWyJOIIRscXm7UmMl"],[5,122.892578125,52.4]],[13,"已 拒 绝",34,34,true,1,-165,[0,"a8SqgepTFAdpIrPbzut15a"],[4,4281824501],[4,4280167304]]],[1,"605O7DC2FDaL9TN4vtpDYH",null,null,null,1,0],[1,0,-226.636,0]],[12,"10:15",40,60,22,[0,"8fNdYOXFtHU7XDAJN7XAIe"]],[5,"返回键 拷贝-001",33554432,10,[[2,-166,[0,"9brxW4y2lFULD/a0UXW4qs"],[5,100,99]]],[1,"77K0xwC+VLMLYYgCE/+iCF",null,null,null,1,0]]],0,[0,4,1,0,0,1,0,0,1,0,0,1,0,0,1,0,0,1,0,5,13,0,6,10,0,7,6,0,8,3,0,9,53,0,0,1,0,-1,11,0,-2,14,0,-3,15,0,-4,3,0,-5,21,0,-6,22,0,-7,12,0,-8,13,0,-9,10,0,0,2,0,-1,23,0,-2,24,0,-3,25,0,-4,26,0,-5,4,0,-6,34,0,-7,35,0,-8,36,0,-9,37,0,-10,38,0,-11,39,0,-12,40,0,-13,41,0,-14,8,0,-15,7,0,-16,9,0,-17,49,0,-18,50,0,-19,51,0,-20,52,0,0,3,0,0,3,0,-1,16,0,-2,17,0,-3,18,0,-4,19,0,-5,20,0,0,4,0,-1,27,0,-2,28,0,-3,29,0,-4,30,0,-5,31,0,-6,32,0,-7,33,0,0,5,0,0,5,0,0,5,0,0,5,0,-1,6,0,0,6,0,0,6,0,0,7,0,0,7,0,-1,44,0,-2,45,0,-3,46,0,0,8,0,0,8,0,-1,42,0,-2,43,0,0,9,0,0,9,0,-1,47,0,-2,48,0,0,10,0,0,10,0,-1,54,0,0,11,0,0,11,0,0,11,0,0,12,0,0,12,0,0,13,0,0,13,0,0,14,0,0,14,0,0,15,0,0,15,0,0,16,0,0,16,0,0,17,0,0,17,0,0,18,0,0,18,0,0,19,0,0,19,0,0,20,0,0,20,0,0,21,0,0,21,0,0,22,0,-2,53,0,0,23,0,0,23,0,0,24,0,0,24,0,0,25,0,0,25,0,0,26,0,0,26,0,0,27,0,0,27,0,0,28,0,0,28,0,0,29,0,0,29,0,0,30,0,0,30,0,0,31,0,0,31,0,0,32,0,0,32,0,0,33,0,0,33,0,0,34,0,0,34,0,0,35,0,0,35,0,0,36,0,0,36,0,0,37,0,0,37,0,0,38,0,0,38,0,0,39,0,0,39,0,0,40,0,0,40,0,0,41,0,0,41,0,0,42,0,0,42,0,0,43,0,0,43,0,0,44,0,0,44,0,0,45,0,0,45,0,0,46,0,0,46,0,0,47,0,0,47,0,0,48,0,0,48,0,0,49,0,0,49,0,0,50,0,0,50,0,0,51,0,0,51,0,0,52,0,0,52,0,0,54,0,10,1,2,3,6,5,3,12,166],[0,0,0,0,0,0,0,0,0,0,0,0,0,0,0,0,0,0,0,0,0,0,0,0],[1,1,1,1,1,1,1,1,1,1,1,1,1,1,1,1,1,1,1,1,1,1,1,1],[1,8,0,0,0,0,0,9,1,1,1,10,11,12,13,14,15,16,17,18,2,2,19,20]],[[{"name":"星星","rect":{"x":0,"y":0,"width":100,"height":100},"offset":{"x":0,"y":0},"originalSize":{"width":100,"height":100},"rotated":false,"capInsets":[0,0,0,0],"vertices":{"rawPosition":[-50,-50,0,50,-50,0,-50,50,0,50,50,0],"indexes":[0,1,2,2,1,3],"uv":[0,100,100,100,0,0,100,0],"nuv":[0,0,1,0,0,1,1,1],"minPos":{"x":-50,"y":-50,"z":0},"maxPos":{"x":50,"y":50,"z":0}},"packable":true,"pixelsToUnit":100,"pivot":{"x":0.5,"y":0.5},"meshType":0}],[0],0,[0],[2],[21]],[[{"name":"图层 82 拷贝 3","rect":{"x":0,"y":0,"width":185,"height":80},"offset":{"x":0,"y":0},"originalSize":{"width":185,"height":80},"rotated":false,"capInsets":[0,0,0,0],"vertices":{"rawPosition":[-92.5,-40,0,92.5,-40,0,-92.5,40,0,92.5,40,0],"indexes":[0,1,2,2,1,3],"uv":[0,80,185,80,0,0,185,0],"nuv":[0,0,1,0,0,1,1,1],"minPos":{"x":-92.5,"y":-40,"z":0},"maxPos":{"x":92.5,"y":40,"z":0}},"packable":true,"pixelsToUnit":100,"pivot":{"x":0.5,"y":0.5},"meshType":0}],[0],0,[0],[2],[22]],[[{"name":"便衣","rect":{"x":0,"y":0,"width":119,"height":119},"offset":{"x":0,"y":0},"originalSize":{"width":119,"height":119},"rotated":false,"capInsets":[0,0,0,0],"vertices":{"rawPosition":[-59.5,-59.5,0,59.5,-59.5,0,-59.5,59.5,0,59.5,59.5,0],"indexes":[0,1,2,2,1,3],"uv":[0,119,119,119,0,0,119,0],"nuv":[0,0,1,0,0,1,1,1],"minPos":{"x":-59.5,"y":-59.5,"z":0},"maxPos":{"x":59.5,"y":59.5,"z":0}},"packable":true,"pixelsToUnit":100,"pivot":{"x":0.5,"y":0.5},"meshType":0}],[0],0,[0],[2],[23]],[[{"name":"图层 116 拷贝 3","rect":{"x":0,"y":0,"width":467,"height":586},"offset":{"x":0,"y":0},"originalSize":{"width":467,"height":586},"rotated":false,"capInsets":[0,0,0,0],"vertices":{"rawPosition":[-233.5,-293,0,233.5,-293,0,-233.5,293,0,233.5,293,0],"indexes":[0,1,2,2,1,3],"uv":[0,586,467,586,0,0,467,0],"nuv":[0,0,1,0,0,1,1,1],"minPos":{"x":-233.5,"y":-293,"z":0},"maxPos":{"x":233.5,"y":293,"z":0}},"packable":true,"pixelsToUnit":100,"pivot":{"x":0.5,"y":0.5},"meshType":0}],[0],0,[0],[2],[24]],[[{"name":"非主流","rect":{"x":0,"y":0,"width":119,"height":119},"offset":{"x":0,"y":0},"originalSize":{"width":119,"height":119},"rotated":false,"capInsets":[0,0,0,0],"vertices":{"rawPosition":[-59.5,-59.5,0,59.5,-59.5,0,-59.5,59.5,0,59.5,59.5,0],"indexes":[0,1,2,2,1,3],"uv":[0,119,119,119,0,0,119,0],"nuv":[0,0,1,0,0,1,1,1],"minPos":{"x":-59.5,"y":-59.5,"z":0},"maxPos":{"x":59.5,"y":59.5,"z":0}},"packable":true,"pixelsToUnit":100,"pivot":{"x":0.5,"y":0.5},"meshType":0}],[0],0,[0],[2],[25]],[[{"name":"广告","rect":{"x":0,"y":0,"width":61,"height":62},"offset":{"x":0,"y":0},"originalSize":{"width":61,"height":62},"rotated":false,"capInsets":[0,0,0,0],"vertices":{"rawPosition":[-30.5,-31,0,30.5,-31,0,-30.5,31,0,30.5,31,0],"indexes":[0,1,2,2,1,3],"uv":[0,62,61,62,0,0,61,0],"nuv":[0,0,1,0,0,1,1,1],"minPos":{"x":-30.5,"y":-31,"z":0},"maxPos":{"x":30.5,"y":31,"z":0}},"packable":true,"pixelsToUnit":100,"pivot":{"x":0.5,"y":0.5},"meshType":0}],[0],0,[0],[2],[26]],[[{"name":"体育","rect":{"x":0,"y":0,"width":119,"height":119},"offset":{"x":0,"y":0},"originalSize":{"width":119,"height":119},"rotated":false,"capInsets":[0,0,0,0],"vertices":{"rawPosition":[-59.5,-59.5,0,59.5,-59.5,0,-59.5,59.5,0,59.5,59.5,0],"indexes":[0,1,2,2,1,3],"uv":[0,119,119,119,0,0,119,0],"nuv":[0,0,1,0,0,1,1,1],"minPos":{"x":-59.5,"y":-59.5,"z":0},"maxPos":{"x":59.5,"y":59.5,"z":0}},"packable":true,"pixelsToUnit":100,"pivot":{"x":0.5,"y":0.5},"meshType":0}],[0],0,[0],[2],[27]],[[{"name":"adccc3d7adb9e37832ba9d669b07214335d4d84e17afc-CVzVN9","rect":{"x":0,"y":0,"width":84,"height":99},"offset":{"x":0,"y":0},"originalSize":{"width":84,"height":99},"rotated":false,"capInsets":[0,0,0,0],"vertices":{"rawPosition":[-42,-49.5,0,42,-49.5,0,-42,49.5,0,42,49.5,0],"indexes":[0,1,2,2,1,3],"uv":[0,99,84,99,0,0,84,0],"nuv":[0,0,1,0,0,1,1,1],"minPos":{"x":-42,"y":-49.5,"z":0},"maxPos":{"x":42,"y":49.5,"z":0}},"packable":true,"pixelsToUnit":100,"pivot":{"x":0.5,"y":0.5},"meshType":0}],[0],0,[0],[2],[28]],[[{"name":"美女","rect":{"x":0,"y":0,"width":119,"height":119},"offset":{"x":0,"y":0},"originalSize":{"width":119,"height":119},"rotated":false,"capInsets":[0,0,0,0],"vertices":{"rawPosition":[-59.5,-59.5,0,59.5,-59.5,0,-59.5,59.5,0,59.5,59.5,0],"indexes":[0,1,2,2,1,3],"uv":[0,119,119,119,0,0,119,0],"nuv":[0,0,1,0,0,1,1,1],"minPos":{"x":-59.5,"y":-59.5,"z":0},"maxPos":{"x":59.5,"y":59.5,"z":0}},"packable":true,"pixelsToUnit":100,"pivot":{"x":0.5,"y":0.5},"meshType":0}],[0],0,[0],[2],[29]]]]
