[1,["bfX4ncwdBCbpOej0MBUV5m@f9941","07e/QFwOhEApsSBfe+zFHz@f9941","6eBFAvPblABJBoId392/BB@f9941","009Tb+mf5NJZWIrUj1uvy1@6c48a","07e/QFwOhEApsSBfe+zFHz@6c48a","2b2qpesNhNj7pZ8s8paEsA@6c48a","6eBFAvPblABJBoId392/BB@6c48a","2b2qpesNhNj7pZ8s8paEsA@f9941","009Tb+mf5NJZWIrUj1uvy1@f9941","bbeAdXShxBCr0w5svOs614@f9941","bbeAdXShxBCr0w5svOs614@6c48a","bfX4ncwdBCbpOej0MBUV5m@6c48a"],["node","_spriteFrame","_textureSource","_parent","root","content","data"],[["cc.Node",["_name","_layer","_components","_prefab","_parent","_children","_lpos","_lscale"],1,9,4,1,2,5,5],"cc.SpriteFrame",["cc.Widget",["_alignFlags","_originalWidth","_originalHeight","_left","_right","_top","_bottom","node","__prefab"],-4,1,4],["cc.Sprite",["_sizeMode","node","__prefab","_spriteFrame","_color"],2,1,4,6,5],["cc.Prefab",["_name"],2],["cc.UITransform",["node","__prefab","_contentSize"],3,1,4,5],["cc.CompPrefabInfo",["fileId"],2],["cc.BlockInputEvents",["node","__prefab"],3,1,4],["b882d+nAexPQp6B0AJkwxEw",["node","__prefab","content"],3,1,4,1],["cc.PrefabInfo",["fileId","instance","targetOverrides","nestedPrefabInstanceRoots","root","asset"],-1,1,1],["cc.Mask",["node","__prefab"],3,1,4],["cc.Graphics",["node","__prefab","_fillColor"],3,1,4,5],["cc.Button",["_transition","node","__prefab","clickEvents"],2,1,4,9],["cc.ClickEvent",["_componentId","handler","target"],1,1]],[[6,0,2],[5,0,1,2,1],[9,0,1,2,3,4,5,5],[3,1,2,3,1],[0,0,1,4,2,3,3],[2,0,1,2,7,8,4],[0,0,1,4,5,2,3,6,7,3],[3,0,1,2,3,2],[0,0,1,5,2,3,3],[12,0,1,2,3,2],[13,0,1,2,3],[0,0,1,4,5,2,3,3],[0,0,1,4,2,3,6,3],[4,0,2],[0,0,1,4,5,2,3,6,3],[0,0,1,4,2,3,6,7,3],[2,0,7,8,2],[2,0,3,4,5,6,1,2,7,8,8],[7,0,1,1],[8,0,1,2,1],[3,0,1,2,4,3,2],[10,0,1,1],[11,0,1,2,1]],[[[{"name":"关闭","rect":{"x":0,"y":0,"width":110,"height":116},"offset":{"x":0,"y":0},"originalSize":{"width":110,"height":116},"rotated":false,"capInsets":[0,0,0,0],"vertices":{"rawPosition":[-55,-58,0,55,-58,0,-55,58,0,55,58,0],"indexes":[0,1,2,2,1,3],"uv":[0,116,110,116,0,0,110,0],"nuv":[0,0,1,0,0,1,1,1],"minPos":{"x":-55,"y":-58,"z":0},"maxPos":{"x":55,"y":58,"z":0}},"packable":true,"pixelsToUnit":100,"pivot":{"x":0.5,"y":0.5},"meshType":0}],[1],0,[0],[2],[3]],[[{"name":"未解锁卡牌","rect":{"x":0,"y":0,"width":244,"height":319},"offset":{"x":0,"y":0},"originalSize":{"width":244,"height":319},"rotated":false,"capInsets":[0,0,0,0],"vertices":{"rawPosition":[-122,-159.5,0,122,-159.5,0,-122,159.5,0,122,159.5,0],"indexes":[0,1,2,2,1,3],"uv":[0,319,244,319,0,0,244,0],"nuv":[0,0,1,0,0,1,1,1],"minPos":{"x":-122,"y":-159.5,"z":0},"maxPos":{"x":122,"y":159.5,"z":0}},"packable":true,"pixelsToUnit":100,"pivot":{"x":0.5,"y":0.5},"meshType":0}],[1],0,[0],[2],[4]],[[{"name":"JJHZ_Mask","rect":{"x":0,"y":0,"width":2,"height":2},"offset":{"x":0,"y":0},"originalSize":{"width":2,"height":2},"rotated":false,"capInsets":[0,0,0,0],"vertices":{"rawPosition":[-1,-1,0,1,-1,0,-1,1,0,1,1,0],"indexes":[0,1,2,2,1,3],"uv":[0,2,2,2,0,0,2,0],"nuv":[0,0,1,0,0,1,1,1],"minPos":{"x":-1,"y":-1,"z":0},"maxPos":{"x":1,"y":1,"z":0}},"packable":true,"pixelsToUnit":100,"pivot":{"x":0.5,"y":0.5},"meshType":0}],[1],0,[0],[2],[5]],[[{"name":"下一页","rect":{"x":0,"y":0,"width":73,"height":88},"offset":{"x":0,"y":0},"originalSize":{"width":73,"height":88},"rotated":false,"capInsets":[0,0,0,0],"vertices":{"rawPosition":[-36.5,-44,0,36.5,-44,0,-36.5,44,0,36.5,44,0],"indexes":[0,1,2,2,1,3],"uv":[0,88,73,88,0,0,73,0],"nuv":[0,0,1,0,0,1,1,1],"minPos":{"x":-36.5,"y":-44,"z":0},"maxPos":{"x":36.5,"y":44,"z":0}},"packable":true,"pixelsToUnit":100,"pivot":{"x":0.5,"y":0.5},"meshType":0}],[1],0,[0],[2],[6]],[[[13,"CharacterCatalogUI"],[8,"CharacterCatalogUI",33554432,[-7,-8],[[1,-2,[0,"10JC8ebzRON4vajkDM3IO6"],[5,2340,1080]],[5,45,100,100,-3,[0,"44MlL/mAVHvZYe2iqae+TH"]],[18,-4,[0,"90yZa4bMRLNrk/1Ug3eoEs"]],[19,-6,[0,"c27hgbvXlDMKNkC62049ta"],-5]],[2,"89NpSwtfBBJpdLKmHu2AFQ",null,null,null,-1,0]],[8,"content",33554432,[-11,-12,-13,-14,-15,-16,-17,-18,-19,-20,-21,-22,-23,-24,-25,-26,-27,-28,-29,-30],[[1,-9,[0,"a2gVn5g7VBgoIV1c1DVlof"],[5,1294,707]],[5,45,174,639.8,-10,[0,"3dyG6r70VABZatPcNmuOeu"]]],[2,"9ehvBNK+lN3YhLyI+eXo5d",null,null,null,1,0]],[11,"图鉴底框",33554432,1,[-33,-34,-35],[[1,-31,[0,"36fUIyCERIGZqsKJjF0ISw"],[5,1494,1057]],[3,-32,[0,"e6PSGUVCJNX7JWT2s6hQpX"],64]],[2,"17/sDEbQdPHLxH5/JGeYIE",null,null,null,1,0]],[8,"view",33554432,[2],[[1,-36,[0,"eb48F6gSZOpJxt7vidFRfW"],[5,1294,707]],[21,-37,[0,"23ebmMDM5ACopXN5kc+xos"]],[22,-38,[0,"111g0ACHFGWIxY8733oM1K"],[4,16777215]],[5,45,240,250,-39,[0,"dfcu19Zy5Nq5lAc2MeVwRg"]]],[2,"37d4DlZItLV4sXsJsj9M7C",null,null,null,1,0]],[6,"0",33554432,2,[-42,-43],[[1,-40,[0,"d0dLEwYupJjpO4w1H7p01y"],[5,348,457]],[3,-41,[0,"615vQowKNILbLV//y6ZWZx"],3]],[2,"36jhDId+lCiK3EUImy9arP",null,null,null,1,0],[1,-490.2,159.95,0],[1,0.6,0.6,1]],[6,"1",33554432,2,[-46,-47],[[1,-44,[0,"16eFm5zuNCjqpz0xi+j4xt"],[5,348,457]],[3,-45,[0,"570w9FeWxO2piMfXi0qB3Q"],6]],[2,"8bTYogX1ZJto4vYpYfelxP",null,null,null,1,0],[1,-246.59999999999997,159.95,0],[1,0.6,0.6,1]],[6,"2",33554432,2,[-50,-51],[[1,-48,[0,"65iBjJErRG1pVn/c6TkwVO"],[5,348,457]],[3,-49,[0,"e0kIzF30BKgaH7q1iggk53"],9]],[2,"b8aePa9KhOt6MdQ22b18/6",null,null,null,1,0],[1,-2.9999999999999716,159.95,0],[1,0.6,0.6,1]],[6,"3",33554432,2,[-54,-55],[[1,-52,[0,"46TW1MxEJNxrB6rLxwcbW6"],[5,348,457]],[3,-53,[0,"e7xs+7VPFKFaKUUhkKvSpL"],12]],[2,"f58ZP2EtdIwI8k0Q6JfWY5",null,null,null,1,0],[1,240.60000000000002,159.95,0],[1,0.6,0.6,1]],[6,"4",33554432,2,[-58,-59],[[1,-56,[0,"96yHGSlCZBc5Hj+E/xNdfP"],[5,348,457]],[3,-57,[0,"d6r7J6DUFPfrvq8AVfTdS+"],15]],[2,"10ev7t1lhIEZA8e5TIhIVm",null,null,null,1,0],[1,484.20000000000005,159.95,0],[1,0.6,0.6,1]],[6,"5",33554432,2,[-62,-63],[[1,-60,[0,"42uEhZfMdN1YPb6gW399te"],[5,348,457]],[3,-61,[0,"a36kTK1YRNSrqxd6euAm8L"],18]],[2,"70H3J/wpZDf7/0SUcSVcNv",null,null,null,1,0],[1,-490.2,-159.95,0],[1,0.6,0.6,1]],[6,"6",33554432,2,[-66,-67],[[1,-64,[0,"114D4EGuxG6aVdSPqmp7QZ"],[5,348,457]],[3,-65,[0,"2aV6iV/Z1LLYNQ9K+ECVWE"],21]],[2,"daHDNa9zpF8JSrne1YSmn3",null,null,null,1,0],[1,-246.59999999999997,-159.95,0],[1,0.6,0.6,1]],[6,"7",33554432,2,[-70,-71],[[1,-68,[0,"d9ansdJjNFtLNgXmQuwwAM"],[5,348,457]],[3,-69,[0,"33qoPcGGVJKZUoYbdR3rJl"],24]],[2,"5cPQfqdSdFbLGj9A0muhzf",null,null,null,1,0],[1,-2.9999999999999716,-159.95,0],[1,0.6,0.6,1]],[6,"8",33554432,2,[-74,-75],[[1,-72,[0,"b4h4lDw/RJk6DNGn50ZMf6"],[5,348,457]],[3,-73,[0,"8bkehOarxJuYrd0JPButO1"],27]],[2,"35yCCsfR1JZY+6nI210acI",null,null,null,1,0],[1,240.60000000000002,-159.95,0],[1,0.6,0.6,1]],[6,"9",33554432,2,[-78,-79],[[1,-76,[0,"de2WvlOIlJHamWEsuWyrW4"],[5,348,457]],[3,-77,[0,"fa4nh1hxJEOqpuBoQakt1K"],30]],[2,"410dt+UlRBHJfPPRlVllX+",null,null,null,1,0],[1,484.20000000000005,-159.95,0],[1,0.6,0.6,1]],[6,"10",33554432,2,[-82,-83],[[1,-80,[0,"d1T+GK0rJNLq6Mrk7U6IRz"],[5,348,457]],[3,-81,[0,"79lu9bmsNLpIqDnko18naU"],33]],[2,"27FIcVyJFCaKHHM3LUa0Cv",null,null,null,1,0],[1,803.8,159.95000000000005,0],[1,0.6,0.6,1]],[6,"11",33554432,2,[-86,-87],[[1,-84,[0,"78A5ByTolAgq8Lnm+0NsuM"],[5,348,457]],[3,-85,[0,"2cHaV4suRIvp734u5B8oKI"],36]],[2,"6dXNuZeBVCLI/iHVjZa82A",null,null,null,1,0],[1,1047.4,159.95000000000005,0],[1,0.6,0.6,1]],[6,"12",33554432,2,[-90,-91],[[1,-88,[0,"0cr20mR3tCgKRSqP+qmaZD"],[5,348,457]],[3,-89,[0,"46Zs29Yl5MJYDxJqonaRU1"],39]],[2,"7fciEac11PY5T3mWb7BmXf",null,null,null,1,0],[1,1291,159.95000000000005,0],[1,0.6,0.6,1]],[6,"13",33554432,2,[-94,-95],[[1,-92,[0,"1a2mW0pU5F/LVIVj+cHgtU"],[5,348,457]],[3,-93,[0,"d0GT+Y9uxCuowj5fvysU+T"],42]],[2,"daHW+8KFpM844SbqO457JG",null,null,null,1,0],[1,1534.6,159.95000000000005,0],[1,0.6,0.6,1]],[6,"14",33554432,2,[-98,-99],[[1,-96,[0,"d98rnqyhJLbYefnaMjCi1G"],[5,348,457]],[3,-97,[0,"26MmK0OkZKmY70RTXneUu1"],45]],[2,"bb4oR7n3hFPpFzhhAetswI",null,null,null,1,0],[1,1778.1999999999998,159.95000000000005,0],[1,0.6,0.6,1]],[6,"15",33554432,2,[-102,-103],[[1,-100,[0,"518byqNy5GqpvU1orrGPy/"],[5,348,457]],[3,-101,[0,"23vT0iu2RJpZyiFys/IeAc"],48]],[2,"b67BnM7y9J4aKtZntK4Sbg",null,null,null,1,0],[1,803.8,-159.95,0],[1,0.6,0.6,1]],[6,"16",33554432,2,[-106,-107],[[1,-104,[0,"7cIQmW+ylOy4CF3wp/XNvw"],[5,348,457]],[3,-105,[0,"1bwUEEElpOkLMRuq0osIth"],51]],[2,"65+PSmHBFCzZ8bxupOOvNt",null,null,null,1,0],[1,1047.4,-159.95,0],[1,0.6,0.6,1]],[6,"17",33554432,2,[-110,-111],[[1,-108,[0,"86Sl1Tt3ZItrq3kv4c8QDW"],[5,348,457]],[3,-109,[0,"e3399TespD3rs4rOteFtsc"],54]],[2,"b2+jaTaYhEGbt9G2fsZ6Rt",null,null,null,1,0],[1,1291,-159.95,0],[1,0.6,0.6,1]],[6,"18",33554432,2,[-114,-115],[[1,-112,[0,"d8wIGsBchKlIokclqTQSo0"],[5,348,457]],[3,-113,[0,"78uCFPkGFP2pkQ16xuQVnO"],57]],[2,"66zKAQA5lLI6IS6EyebQ1d",null,null,null,1,0],[1,1534.6,-159.95,0],[1,0.6,0.6,1]],[6,"19",33554432,2,[-118,-119],[[1,-116,[0,"07L1DpF2tPq4Y2eu0MSOYU"],[5,348,457]],[3,-117,[0,"98rB0dlwBE1qe2w688gOyg"],60]],[2,"afMsUgdaBHFKrVfv5lCSR+",null,null,null,1,0],[1,1778.1999999999998,-159.95,0],[1,0.6,0.6,1]],[11,"buttons",33554432,3,[-122,-123],[[1,-120,[0,"12NhTIrUpIrqIvDguOhm/X"],[5,1494,1057]],[5,45,100,100,-121,[0,"39qu8A93NKu41tYzYjbuiX"]]],[2,"e09IaDRtlBaqsM8Czr7sKG",null,null,null,1,0]],[12,"关闭",33554432,3,[[1,-124,[0,"753u/9yIRAO5PNpiYyirYh"],[5,110,116]],[3,-125,[0,"c23YkY87dCpbfK3Vj7DmEY"],63],[16,33,-126,[0,"28dnxcGzBEh54ifpTKZfPt"]],[9,3,-127,[0,"d8FDjGsGhGlqY3VDCBqBgL"],[[10,"b882d+nAexPQp6B0AJkwxEw","Close",1]]]],[2,"bfuw8hUApLuKa7rR/NnRiU",null,null,null,1,0],[1,692,470.5,0]],[4,"bg",33554432,1,[[1,-128,[0,"5afaihUAJHlqLpgJcRhaFv"],[5,2340,1080]],[20,0,-129,[0,"db6pAct3tN144qUL8aLq5z"],[4,2147483648],0],[5,45,100,100,-130,[0,"adqNdW4MBG15dfrlGDnJOW"]]],[2,"8c33d7rNBPE7ubR6v+1nfq",null,null,null,1,0]],[14,"ScrollView",33554432,3,[4],[[1,-131,[0,"49lwpKrYhCM7CPidgdUsy0"],[5,1294,707]],[17,45,100,100,200,150,240,250,-132,[0,"b5gP/JZftO0qfFNntvql3g"]]],[2,"2bQkVCsYtGM5ginhOxJycr",null,null,null,1,0],[1,0,-25,0]],[4,"普通卡包_刮层",33554432,5,[[1,-133,[0,"fehAL0u/VCB4s9bnUyaKB0"],[5,348,457]],[7,0,-134,[0,"31YaUMwFZGA5Z8N0kbnE/I"],2],[5,45,244,319,-135,[0,"8dv2sT5slKUJH3ftTv3j6L"]]],[2,"05KcMDighKyah3Rx1YB7YD",null,null,null,1,0]],[4,"普通卡包_刮层",33554432,6,[[1,-136,[0,"a0NmoBiDlO/LEoOlanUwIq"],[5,348,457]],[7,0,-137,[0,"93P+/OhpBFKr05mNHLMCJP"],5],[5,45,244,319,-138,[0,"efAMqeaWtNKb1DADpCJhFi"]]],[2,"a5f1GgkZNKs4rPN0gkRIRK",null,null,null,1,0]],[4,"普通卡包_刮层",33554432,7,[[1,-139,[0,"79gc4/Ma9KrIIfAJcvlcu1"],[5,348,457]],[7,0,-140,[0,"e5Xdvi2xdBeKDkDNHruQGZ"],8],[5,45,244,319,-141,[0,"66djhBZ/hB14AwBhUzuAmU"]]],[2,"9fq3d3CpZAV5oBIxQKy+kO",null,null,null,1,0]],[4,"普通卡包_刮层",33554432,8,[[1,-142,[0,"ecvn3bpxdBmbZB2R0b8guS"],[5,348,457]],[7,0,-143,[0,"ebzDgrwO1FjJX04ghrM2WD"],11],[5,45,244,319,-144,[0,"6bLChHi/hGeaaVpUP0HL6o"]]],[2,"02MAHTGiBHCrFPLULIut1T",null,null,null,1,0]],[4,"普通卡包_刮层",33554432,9,[[1,-145,[0,"caBIWCN9FEJJXTgyNl4UC/"],[5,348,457]],[7,0,-146,[0,"85k3plU8xMipIlUB5ZI08U"],14],[5,45,244,319,-147,[0,"47wq89P7NMobsZktqFgChJ"]]],[2,"68iet9jPdHh5xdTNv1/GUN",null,null,null,1,0]],[4,"普通卡包_刮层",33554432,10,[[1,-148,[0,"a1wYyE94dO+L+UOi/lg/FV"],[5,348,457]],[7,0,-149,[0,"9aOuUU/+JDza2sFMPiZwkP"],17],[5,45,244,319,-150,[0,"90Blc8JklPHpmZILRHffqQ"]]],[2,"565bpboOVNaoZ/7Jh5cWej",null,null,null,1,0]],[4,"普通卡包_刮层",33554432,11,[[1,-151,[0,"0djkqHkaFIZ7gn3PCAxsbq"],[5,348,457]],[7,0,-152,[0,"6bCAkI7GxAMogU3wQ4Xbse"],20],[5,45,244,319,-153,[0,"86gaChLdFBpZXx6K7F29Hy"]]],[2,"beBEc7q0xEn5wUmEpJ4nfB",null,null,null,1,0]],[4,"普通卡包_刮层",33554432,12,[[1,-154,[0,"70hcXKhWRIYIB6VOBt3zlv"],[5,348,457]],[7,0,-155,[0,"e0gVRueCdI/bmP+QtOsu7X"],23],[5,45,244,319,-156,[0,"f8BaXFJRRAFaqOc3WoNbo0"]]],[2,"78p44VJntOMLXkjOR1ZeTv",null,null,null,1,0]],[4,"普通卡包_刮层",33554432,13,[[1,-157,[0,"e3dO1yPiZMqY3q3hBWC8l+"],[5,348,457]],[7,0,-158,[0,"0eeEHBNlFKtaJlVmUaeyvg"],26],[5,45,244,319,-159,[0,"017mUeRH1Iir/zR+nkQVUJ"]]],[2,"dam5NKc3ZJ8Z5o/Mezu9Jw",null,null,null,1,0]],[4,"普通卡包_刮层",33554432,14,[[1,-160,[0,"a5pCOPU3BCMIBN1h+Wx9w9"],[5,348,457]],[7,0,-161,[0,"feTKNTYvxJdayOhW6w2G0P"],29],[5,45,244,319,-162,[0,"d0G1FvETNPGp5MfzupM/Xb"]]],[2,"a9nepGIf1K7aZlLKYFYFZs",null,null,null,1,0]],[4,"普通卡包_刮层",33554432,15,[[1,-163,[0,"b0G13oDIBB4JU6B5cdLjCX"],[5,348,457]],[7,0,-164,[0,"76/Bd2P/xMaZVWB9VnRd/v"],32],[5,45,244,319,-165,[0,"7fhrYPGllBZoju3qSugkNx"]]],[2,"c2+owo8oxE3qTwH9Ma8JrY",null,null,null,1,0]],[4,"普通卡包_刮层",33554432,16,[[1,-166,[0,"fe6z8QwbNEB65H0O+CW/iD"],[5,348,457]],[7,0,-167,[0,"881gHeGbNBUbr6K7HKSd9K"],35],[5,45,244,319,-168,[0,"1avMPMh45EQK2rV4K9DHwz"]]],[2,"7bte6HpDRK9KxHB1jUF2DW",null,null,null,1,0]],[4,"普通卡包_刮层",33554432,17,[[1,-169,[0,"ccbhGnwxFFVprDGnKo5iNa"],[5,348,457]],[7,0,-170,[0,"1bc69E4qJKWa3VycShknQR"],38],[5,45,244,319,-171,[0,"93Dn7+d/1Ptrw6QJIVlSlu"]]],[2,"7d7ji4EsNJlJ89NrE9cbRs",null,null,null,1,0]],[4,"普通卡包_刮层",33554432,18,[[1,-172,[0,"b2eTeCmv9NS6H+JOdkzOv3"],[5,348,457]],[7,0,-173,[0,"deysZa9+FDMLLQDMh71BYo"],41],[5,45,244,319,-174,[0,"ffOvcy0f5P+IsrsoIwJKoG"]]],[2,"abFebQAhZHcqkySfr0qEuy",null,null,null,1,0]],[4,"普通卡包_刮层",33554432,19,[[1,-175,[0,"8agduDS59DjZvAbrGnfpfa"],[5,348,457]],[7,0,-176,[0,"8dOtvasb9NbbiOC9U1x8+Q"],44],[5,45,244,319,-177,[0,"69HEjysc9EmJ2+FfEK6wOD"]]],[2,"63l3355lFPVKG6iMpUgQfV",null,null,null,1,0]],[4,"普通卡包_刮层",33554432,20,[[1,-178,[0,"f1MRlEWZBMmpl9oQCKdfoG"],[5,348,457]],[7,0,-179,[0,"67UYh/AsZNpKRmjgCXPwCH"],47],[5,45,244,319,-180,[0,"65bVfdQCdHsqYswH70KSUT"]]],[2,"6av+9mK5FK1pmwwXCV/lpx",null,null,null,1,0]],[4,"普通卡包_刮层",33554432,21,[[1,-181,[0,"9eMdLx6sJLyKasRqH1wRZT"],[5,348,457]],[7,0,-182,[0,"f9sPbFL+dF3J7WQuz7TP4f"],50],[5,45,244,319,-183,[0,"71CMya7BZEtrJF+MfrUptM"]]],[2,"609Hkzt8dPDrtKc8UWhLua",null,null,null,1,0]],[4,"普通卡包_刮层",33554432,22,[[1,-184,[0,"61w3iSzhJLa7IwbX92+OkM"],[5,348,457]],[7,0,-185,[0,"62Fn1/XZtIS4QGmrarYSJY"],53],[5,45,244,319,-186,[0,"9cpzh85JtEgJ/mFwXiR+r3"]]],[2,"a0SSfKdJBGqIAJoJVKRqIh",null,null,null,1,0]],[4,"普通卡包_刮层",33554432,23,[[1,-187,[0,"c0PNrIhAVKSpM7oCGuBlIc"],[5,348,457]],[7,0,-188,[0,"567hpNqUtMp4Q5ynSftvfM"],56],[5,45,244,319,-189,[0,"08zBwhRY9AcpVG8N/YQ5gA"]]],[2,"f4t+VKRglKxrYZpXQqwGH9",null,null,null,1,0]],[4,"普通卡包_刮层",33554432,24,[[1,-190,[0,"24nCV1ZBRKKLwa6KcxUnYF"],[5,348,457]],[7,0,-191,[0,"626MhbEFhEEpk+4yyMlGJ1"],59],[5,45,244,319,-192,[0,"fdjlXkvBFICY4BNNHYqbY8"]]],[2,"25F9TNn4xLjLgJtUPuVaTU",null,null,null,1,0]],[15,"下一页",33554432,25,[[1,-193,[0,"69xea/7lZO5ZK3HZSizGXv"],[5,73,88]],[3,-194,[0,"79jThaSY9Fo7u8v0DuisLm"],61],[9,3,-195,[0,"4e7s4SZRxAK6uugGXykgVn"],[[10,"b882d+nAexPQp6B0AJkwxEw","Page",1]]]],[2,"62xwYPVyBNwKvLeHhVghir",null,null,null,1,0],[1,-700,0,0],[1,-1,1,1]],[12,"下一页-001",33554432,25,[[1,-196,[0,"8ah2c2Dj9Dnb+EXOsraSR6"],[5,73,88]],[3,-197,[0,"85KsoAncVFJrS9vvVBS7FN"],62],[9,3,-198,[0,"6b5g0nVRhGDIyBkjKOW+3y"],[[10,"b882d+nAexPQp6B0AJkwxEw","Page",1]]]],[2,"49PmAxaDJNLr1gbvXGRUHP",null,null,null,1,0],[1,700,0,0]],[4,"0",33554432,5,[[1,-199,[0,"62gJdd35FMcI8H1M2QqJTT"],[5,348,457]],[3,-200,[0,"8cGVzq+htB35GL8ws6ewtQ"],1]],[2,"18ru1KnHpLsYNyyWnFcXUP",null,null,null,1,0]],[4,"0",33554432,6,[[1,-201,[0,"38AaN+XmlKLKawgUQFXqIc"],[5,348,457]],[3,-202,[0,"50EmjwMRxMnao0XayfEOCn"],4]],[2,"8bFEYOuhNOab4BCTnSh+mU",null,null,null,1,0]],[4,"0",33554432,7,[[1,-203,[0,"82KZtKFrBFvrpdBEP1q0ld"],[5,348,457]],[3,-204,[0,"50qwqLHGhCHrX5imIPZdP4"],7]],[2,"0f7lmXxa9ESa1b0C7JKkvP",null,null,null,1,0]],[4,"0",33554432,8,[[1,-205,[0,"70ad+DUbZNBpcQ89qBGe0A"],[5,348,457]],[3,-206,[0,"65u+7NdYhEVaw4BnOp7Y6N"],10]],[2,"b5rZAGzCZMLZCQBAIxn6Cv",null,null,null,1,0]],[4,"0",33554432,9,[[1,-207,[0,"4buxTCR5hNJZDR/XpoZl2q"],[5,348,457]],[3,-208,[0,"c0iwk176FNA6miLu3Ore9L"],13]],[2,"36QfinvftBkoROkF/xbSSV",null,null,null,1,0]],[4,"0",33554432,10,[[1,-209,[0,"9bJ8ro/ZlCXLO/bStDbG/x"],[5,348,457]],[3,-210,[0,"d6Tc+RjqBMCoZUZQz2krT3"],16]],[2,"bdZTW9Dn5GX6MNBv5xgAjQ",null,null,null,1,0]],[4,"0",33554432,11,[[1,-211,[0,"2eGS1/MUVChYGbfA60ot2j"],[5,348,457]],[3,-212,[0,"1bMAKvFblP0IGs1Yfzf4mE"],19]],[2,"189F7G+CxK844W9hXeLrFi",null,null,null,1,0]],[4,"0",33554432,12,[[1,-213,[0,"2fFyWoDuZBTIYuMZzWNXUF"],[5,348,457]],[3,-214,[0,"e1k746iHdGZI5kYw/A6ZqD"],22]],[2,"12YK+K8SVJtZ+X6OCp2SUY",null,null,null,1,0]],[4,"0",33554432,13,[[1,-215,[0,"92T4cGUndCqpx/knYca1QB"],[5,348,457]],[3,-216,[0,"b2TgXOM/1O9q8j1jrrXPbG"],25]],[2,"76NRDUXKdElreQqHhY4Kza",null,null,null,1,0]],[4,"0",33554432,14,[[1,-217,[0,"2dzdCGW8xJjbvWUIl0svGK"],[5,348,457]],[3,-218,[0,"3c3NOFUD9BhqbrFuG/1eoo"],28]],[2,"7csUmDQwhFDbSBgF3rXvBC",null,null,null,1,0]],[4,"0",33554432,15,[[1,-219,[0,"67KMg4QMVL/LMgYtB2jNbh"],[5,348,457]],[3,-220,[0,"6c4J4C4oNKvbJ7NF0cxpnH"],31]],[2,"bfiFM4WJZKU4Fa8YoBm1PO",null,null,null,1,0]],[4,"0",33554432,16,[[1,-221,[0,"78Bk1do5ZNJZaAWSdLIw14"],[5,348,457]],[3,-222,[0,"fcWm0wZb5H8JR3LGNoTLp5"],34]],[2,"67wMSTGAlCSIQQ0tWgvhuf",null,null,null,1,0]],[4,"0",33554432,17,[[1,-223,[0,"25HEtmfaRFQ4fH1kklvlrL"],[5,348,457]],[3,-224,[0,"25P4zDV1BPq5P4IH89ix02"],37]],[2,"687aa9/TlM14gRuHSxrij3",null,null,null,1,0]],[4,"0",33554432,18,[[1,-225,[0,"d3wQqd/J9Aood26cvs5tIE"],[5,348,457]],[3,-226,[0,"36YSrtBJNH05aaRj3lqOmA"],40]],[2,"e6z3sxDHNPFqjQ4oZfrbiH",null,null,null,1,0]],[4,"0",33554432,19,[[1,-227,[0,"8eXfgvxtNFOIyAznQxbnXi"],[5,348,457]],[3,-228,[0,"0fXmprdZFAVrFdarxEh0vR"],43]],[2,"6dkETxCLRFw4/kYsvpiBzH",null,null,null,1,0]],[4,"0",33554432,20,[[1,-229,[0,"73ElbuIONMpZINpmPAC0wf"],[5,348,457]],[3,-230,[0,"44PvjsKgBGJY+a2PN9hlqh"],46]],[2,"97Hzopr6NFJLWnucK00M1f",null,null,null,1,0]],[4,"0",33554432,21,[[1,-231,[0,"0cTDvpBfxBN6d2eYxMgESk"],[5,348,457]],[3,-232,[0,"7aNwaEFjVPl6Npl+j19JLq"],49]],[2,"f1ZI48d7BJ8YAe1J+r0CGB",null,null,null,1,0]],[4,"0",33554432,22,[[1,-233,[0,"7bBtV4HxFEG53awPwAN/E9"],[5,348,457]],[3,-234,[0,"26U6mUoR9LdqsJyU7oM3hi"],52]],[2,"a0EDRvufNECY4P5DJ4HTqy",null,null,null,1,0]],[4,"0",33554432,23,[[1,-235,[0,"89/bedp8BCN4I/Xh0TnmE2"],[5,348,457]],[3,-236,[0,"fc4LaO611Ku4sWy7kN2c1d"],55]],[2,"12SmccSQRGiaEBcMihz6HY",null,null,null,1,0]],[4,"0",33554432,24,[[1,-237,[0,"ecfNHpuxxI04aXSYJ0RTze"],[5,348,457]],[3,-238,[0,"06R83ltXFHlboJzc7iAbPJ"],58]],[2,"131S24uqRI2YgltJoCMaUT",null,null,null,1,0]]],0,[0,4,1,0,0,1,0,0,1,0,0,1,0,5,2,0,0,1,0,-1,27,0,-2,3,0,0,2,0,0,2,0,-1,5,0,-2,6,0,-3,7,0,-4,8,0,-5,9,0,-6,10,0,-7,11,0,-8,12,0,-9,13,0,-10,14,0,-11,15,0,-12,16,0,-13,17,0,-14,18,0,-15,19,0,-16,20,0,-17,21,0,-18,22,0,-19,23,0,-20,24,0,0,3,0,0,3,0,-1,28,0,-2,25,0,-3,26,0,0,4,0,0,4,0,0,4,0,0,4,0,0,5,0,0,5,0,-1,51,0,-2,29,0,0,6,0,0,6,0,-1,52,0,-2,30,0,0,7,0,0,7,0,-1,53,0,-2,31,0,0,8,0,0,8,0,-1,54,0,-2,32,0,0,9,0,0,9,0,-1,55,0,-2,33,0,0,10,0,0,10,0,-1,56,0,-2,34,0,0,11,0,0,11,0,-1,57,0,-2,35,0,0,12,0,0,12,0,-1,58,0,-2,36,0,0,13,0,0,13,0,-1,59,0,-2,37,0,0,14,0,0,14,0,-1,60,0,-2,38,0,0,15,0,0,15,0,-1,61,0,-2,39,0,0,16,0,0,16,0,-1,62,0,-2,40,0,0,17,0,0,17,0,-1,63,0,-2,41,0,0,18,0,0,18,0,-1,64,0,-2,42,0,0,19,0,0,19,0,-1,65,0,-2,43,0,0,20,0,0,20,0,-1,66,0,-2,44,0,0,21,0,0,21,0,-1,67,0,-2,45,0,0,22,0,0,22,0,-1,68,0,-2,46,0,0,23,0,0,23,0,-1,69,0,-2,47,0,0,24,0,0,24,0,-1,70,0,-2,48,0,0,25,0,0,25,0,-1,49,0,-2,50,0,0,26,0,0,26,0,0,26,0,0,26,0,0,27,0,0,27,0,0,27,0,0,28,0,0,28,0,0,29,0,0,29,0,0,29,0,0,30,0,0,30,0,0,30,0,0,31,0,0,31,0,0,31,0,0,32,0,0,32,0,0,32,0,0,33,0,0,33,0,0,33,0,0,34,0,0,34,0,0,34,0,0,35,0,0,35,0,0,35,0,0,36,0,0,36,0,0,36,0,0,37,0,0,37,0,0,37,0,0,38,0,0,38,0,0,38,0,0,39,0,0,39,0,0,39,0,0,40,0,0,40,0,0,40,0,0,41,0,0,41,0,0,41,0,0,42,0,0,42,0,0,42,0,0,43,0,0,43,0,0,43,0,0,44,0,0,44,0,0,44,0,0,45,0,0,45,0,0,45,0,0,46,0,0,46,0,0,46,0,0,47,0,0,47,0,0,47,0,0,48,0,0,48,0,0,48,0,0,49,0,0,49,0,0,49,0,0,50,0,0,50,0,0,50,0,0,51,0,0,51,0,0,52,0,0,52,0,0,53,0,0,53,0,0,54,0,0,54,0,0,55,0,0,55,0,0,56,0,0,56,0,0,57,0,0,57,0,0,58,0,0,58,0,0,59,0,0,59,0,0,60,0,0,60,0,0,61,0,0,61,0,0,62,0,0,62,0,0,63,0,0,63,0,0,64,0,0,64,0,0,65,0,0,65,0,0,66,0,0,66,0,0,67,0,0,67,0,0,68,0,0,68,0,0,69,0,0,69,0,0,70,0,0,70,0,6,1,2,3,4,4,3,28,238],[0,0,0,0,0,0,0,0,0,0,0,0,0,0,0,0,0,0,0,0,0,0,0,0,0,0,0,0,0,0,0,0,0,0,0,0,0,0,0,0,0,0,0,0,0,0,0,0,0,0,0,0,0,0,0,0,0,0,0,0,0,0,0,0,0],[1,1,1,1,1,1,1,1,1,1,1,1,1,1,1,1,1,1,1,1,1,1,1,1,1,1,1,1,1,1,1,1,1,1,1,1,1,1,1,1,1,1,1,1,1,1,1,1,1,1,1,1,1,1,1,1,1,1,1,1,1,1,1,1,1],[7,0,1,0,0,1,0,0,1,0,0,1,0,0,1,0,0,1,0,0,1,0,0,1,0,0,1,0,0,1,0,0,1,0,0,1,0,0,1,0,0,1,0,0,1,0,0,1,0,0,1,0,0,1,0,0,1,0,0,1,0,2,2,8,9]],[[{"name":"图鉴底框","rect":{"x":0,"y":0,"width":1494,"height":1057},"offset":{"x":0,"y":0},"originalSize":{"width":1494,"height":1057},"rotated":false,"capInsets":[0,0,0,0],"vertices":{"rawPosition":[-747,-528.5,0,747,-528.5,0,-747,528.5,0,747,528.5,0],"indexes":[0,1,2,2,1,3],"uv":[0,1057,1494,1057,0,0,1494,0],"nuv":[0,0,1,0,0,1,1,1],"minPos":{"x":-747,"y":-528.5,"z":0},"maxPos":{"x":747,"y":528.5,"z":0}},"packable":true,"pixelsToUnit":100,"pivot":{"x":0.5,"y":0.5},"meshType":0}],[1],0,[0],[2],[10]],[[{"name":"0","rect":{"x":0,"y":0,"width":348,"height":457},"offset":{"x":0,"y":0},"originalSize":{"width":348,"height":457},"rotated":false,"capInsets":[0,0,0,0],"vertices":{"rawPosition":[-174,-228.5,0,174,-228.5,0,-174,228.5,0,174,228.5,0],"indexes":[0,1,2,2,1,3],"uv":[0,457,348,457,0,0,348,0],"nuv":[0,0,1,0,0,1,1,1],"minPos":{"x":-174,"y":-228.5,"z":0},"maxPos":{"x":174,"y":228.5,"z":0}},"packable":true,"pixelsToUnit":100,"pivot":{"x":0.5,"y":0.5},"meshType":0}],[1],0,[0],[2],[11]]]]
