[1,["8cTKAwCCFOyLwszixDJnRb@6c48a","23sc4wE3JBEZjPebM9NGG9@f9941","80LqWu21BATp1wCB5+KMSe@f9941","8cTKAwCCFOyLwszixDJnRb@f9941","90XtXKSQhIzpEYstB4wVFy@f9941","b4JiGEfD1I3rhvyTU7ZBE5@f9941"],["node","_spriteFrame","_textureSource","root","_target","data","_parent"],[["cc.Node",["_name","_layer","_components","_prefab","_children","_parent","_lpos"],1,9,4,2,1,5],["cc.Sprite",["_type","_sizeMode","node","__prefab","_spriteFrame","_color"],1,1,4,6,5],["cc.Widget",["_alignFlags","_top","_originalWidth","_originalHeight","_right","node","__prefab"],-2,1,4],["cc.Button",["_transition","node","__prefab","clickEvents","_target"],2,1,4,9,1],["cc.Label",["_string","_actualFontSize","_fontSize","_lineHeight","_isBold","_enableOutline","_outlineWidth","node","__prefab","_color"],-4,1,4,5],"cc.SpriteFrame",["cc.Prefab",["_name"],2],["cc.UITransform",["node","__prefab","_contentSize"],3,1,4,5],["cc.CompPrefabInfo",["fileId"],2],["cc.BlockInputEvents",["node","__prefab"],3,1,4],["64359qbSz5OrpFYIvwv8QXe",["node","__prefab"],3,1,4],["cc.PrefabInfo",["fileId","instance","targetOverrides","nestedPrefabInstanceRoots","root","asset"],-1,1,1],["cc.ClickEvent",["_componentId","handler","target"],1,1],["cc.Layout",["_enabled","_resizeMode","_layoutType","_spacingY","node","__prefab"],-1,1,4]],[[8,0,2],[7,0,1,2,1],[11,0,1,2,3,4,5,5],[0,0,1,5,2,3,6,3],[12,0,1,2,3],[2,0,1,5,6,3],[0,0,1,5,4,2,3,6,3],[2,0,2,3,5,6,4],[9,0,1,1],[1,0,1,2,3,4,3],[3,0,1,2,3,2],[4,0,1,2,3,4,5,6,7,8,8],[6,0,2],[0,0,1,4,2,3,3],[0,0,1,5,4,2,3,3],[0,0,1,4,2,3,6,3],[0,0,1,5,2,3,3],[2,0,4,1,5,6,4],[10,0,1,1],[1,0,2,3,4,2],[1,1,2,3,5,4,2],[1,2,3,4,1],[3,0,1,2,3,4,2],[3,1,2,3,1],[13,0,1,2,3,4,5,5],[4,0,1,2,3,4,7,8,9,6]],[[[{"name":"Button_Pink","rect":{"x":0,"y":0,"width":315,"height":158},"offset":{"x":0,"y":0},"originalSize":{"width":315,"height":158},"rotated":false,"capInsets":[50,0,50,0],"vertices":{"rawPosition":[-157.5,-79,0,157.5,-79,0,-157.5,79,0,157.5,79,0],"indexes":[0,1,2,2,1,3],"uv":[0,158,315,158,0,0,315,0],"nuv":[0,0,1,0,0,1,1,1],"minPos":{"x":-157.5,"y":-79,"z":0},"maxPos":{"x":157.5,"y":79,"z":0}},"packable":true,"pixelsToUnit":100,"pivot":{"x":0.5,"y":0.5},"meshType":0}],[5],0,[0],[2],[0]],[[[12,"BaconPausePanel"],[13,"BaconPausePanel",33554432,[-6,-7],[[1,-2,[0,"2bDg/qsp9AG6CmelvDwfer"],[5,2340,1080]],[7,45,100,100,-3,[0,"3cMTlE9VpK9YfyGQy5NZCl"]],[8,-4,[0,"bak7iwjP1P2qptoG+lMtiR"]],[18,-5,[0,"d5Y4/MEM1KzJkc09GLXhAd"]]],[2,"17Uzu3VENPQa1SvM0y3NHe",null,null,null,-1,0]],[14,"Panel",33554432,1,[-11,-12,-13],[[1,-8,[0,"0c3m6jGQBIxZeuUsnJ0JhV"],[5,709,816]],[19,1,-9,[0,"f28IYYhZRHnaJHs5IFuzXI"],4],[8,-10,[0,"820i2liYBCzaDEPti0QbVS"]]],[2,"d2a1vPq4NBDY/tnJ5eQBqK",null,null,null,1,0]],[15,"ReturnButton",33554432,[-18],[[1,-14,[0,"b62+8MwlRHC5kbqAOAmfU7"],[5,361.592,110.6]],[9,1,0,-15,[0,"68gLch0HtP1r61XqCJyMgP"],2],[22,3,-17,[0,"1b24QliEhKN4ZXD/JbMJEV"],[[4,"64359qbSz5OrpFYIvwv8QXe","OnButtonClick",1]],-16]],[2,"f9lLlyJ4BL9Kz1OmMCKe9w",null,null,null,1,0],[1,0,80.3,0]],[16,"Mask",33554432,1,[[1,-19,[0,"559F+mU0NGN7N8+TXUp4pP"],[5,2340,1080]],[20,0,-20,[0,"13ios73+9BjL2Bnv9UOl0p"],[4,2516582400],0],[7,45,100,100,-21,[0,"aaqG6MbppEAbqWzxfpwqvH"]],[23,-22,[0,"95s9cw2TNBiLWvKtg4hkGo"],[[4,"64359qbSz5OrpFYIvwv8QXe","OnButtonClick",1]]]],[2,"48z0sHjyVH47EynUkbaEMw",null,null,null,1,0]],[3,"CloseButton",33554432,2,[[1,-23,[0,"29K/tYY2hA7IMp2dRJZzLS"],[5,94,94]],[21,-24,[0,"52sLEFwttA356qZfVNKshL"],1],[17,33,6.9480000000000075,-69.636,-25,[0,"5as6i8gU9MP6qHJ8WBc9Yv"]],[10,3,-26,[0,"d512FTAWlBsadwsjKoMIc7"],[[4,"64359qbSz5OrpFYIvwv8QXe","OnButtonClick",1]]]],[2,"fbiu9BVutL0a0p3K5YkdNd",null,null,null,1,0],[1,300.552,430.63599999999997,0]],[6,"Buttons",33554432,2,[3,-29],[[1,-27,[0,"bfveMnxZlPMaAIAlajwFuU"],[5,100,271.2]],[24,false,1,2,50,-28,[0,"91bppnpvZKfZ5UZlAxG3jf"]]],[2,"f6L2pWPoVId6XFf/m0aTuD",null,null,null,1,0],[1,0,-50,0]],[6,"ResumeButton",33554432,6,[-33],[[1,-30,[0,"47AsjijP9OPqhkHtMuo3zq"],[5,361.592,110.6]],[9,1,0,-31,[0,"9bg3DHjNxCBqLd1ZDHCM4N"],3],[10,3,-32,[0,"1ed1VaBspNu6uSoE3qnB4v"],[[4,"64359qbSz5OrpFYIvwv8QXe","OnButtonClick",1]]]],[2,"2fwhq7UgBDYrBshJVh1whP",null,null,null,1,0],[1,0,-80.3,0]],[3,"TitleLb",33554432,2,[[1,-34,[0,"4f51S0/pJB7KYr8BHr9Oj8"],[5,120,75.6]],[25,"暂停",60,60,60,true,-35,[0,"93uxJaI1hDlJXC1C36L4+1"],[4,4278190080]],[5,1,25.159999999999968,-36,[0,"14beYGql5PaZn7CgMFTZcu"]]],[2,"dewb9iR9hJ/r6XuoYuhZE7",null,null,null,1,0],[1,0,345.04,0]],[3,"Label",33554432,3,[[1,-37,[0,"b0s49qLG5Ewbs5KyEGnwMD"],[5,186,62.7]],[11,"返回主页",45,45,45,true,true,3,-38,[0,"6fqVImorVLDbDpArVmjBfs"]],[5,1,17.949999999999996,-39,[0,"10aJP6ZsNCLbJEve3333mL"]]],[2,"37xJnWCqtBoYydQzyN3RwN",null,null,null,1,0],[1,0,6,0]],[3,"Label",33554432,7,[[1,-40,[0,"f9HK+77uJE+7m0yvlgUcp2"],[5,186,62.7]],[11,"继续游戏",45,45,45,true,true,3,-41,[0,"67t5bvLJNN6piuYpJ23YFd"]],[5,1,17.949999999999996,-42,[0,"f8/3r3AqdBNYeTVeAI7rkn"]]],[2,"b95+5+QIJLB5Gpj8/AgSOY",null,null,null,1,0],[1,0,6,0]]],0,[0,3,1,0,0,1,0,0,1,0,0,1,0,0,1,0,-1,4,0,-2,2,0,0,2,0,0,2,0,0,2,0,-1,8,0,-2,5,0,-3,6,0,0,3,0,0,3,0,4,3,0,0,3,0,-1,9,0,0,4,0,0,4,0,0,4,0,0,4,0,0,5,0,0,5,0,0,5,0,0,5,0,0,6,0,0,6,0,-2,7,0,0,7,0,0,7,0,0,7,0,-1,10,0,0,8,0,0,8,0,0,8,0,0,9,0,0,9,0,0,9,0,0,10,0,0,10,0,0,10,0,5,1,3,6,6,42],[0,0,0,0,0],[1,1,1,1,1],[1,2,3,4,5]]]]
