[1,["09MF9PJK9OeKXZAnO2S2Nd@6c48a","21rIWwW7JAfIdBmp4qkMXM@6c48a","303eWCCs5E/Kdo5EZvM7iB@6c48a","37VOng0fhPPYfC7T8lbodR@6c48a","4bf+PSAaJBXL5vKOsuk2Wk@6c48a","70o5Nw5uJIE4WjFa7bMpjZ@6c48a","76cmFcD55HvqLrLk9lOx0J@6c48a","8b/enBWKVCOrmKKC94sqTQ@6c48a","a3TWoI45xItagWWDCOwxYm@6c48a","a7+WkWryhPxq907U6Pfg3O@6c48a","d1/KgRd1JP+ZRdey6KEzuX@6c48a","deyMxw1kxHEq6dknWEyofq@6c48a","df0qrUMwhGDbV5CXxGXAOd@6c48a","e6WaaDibZJYoNz3rbatNhb@6c48a","f1ZYtE/rdAaKRCtInfhZIP@6c48a"],["_textureSource"],["cc.SpriteFrame"],0,[[[{"name":"4","rect":{"x":0,"y":0,"width":550,"height":900},"offset":{"x":0,"y":0},"originalSize":{"width":550,"height":900},"rotated":false,"capInsets":[0,0,0,0],"vertices":{"rawPosition":[-275,-450,0,275,-450,0,-275,450,0,275,450,0],"indexes":[0,1,2,2,1,3],"uv":[0,900,550,900,0,0,550,0],"nuv":[0,0,1,0,0,1,1,1],"minPos":{"x":-275,"y":-450,"z":0},"maxPos":{"x":275,"y":450,"z":0}},"packable":true,"pixelsToUnit":100,"pivot":{"x":0.5,"y":0.5},"meshType":0}],[0],0,[0],[0],[0]],[[{"name":"3","rect":{"x":0,"y":0,"width":550,"height":900},"offset":{"x":0,"y":0},"originalSize":{"width":550,"height":900},"rotated":false,"capInsets":[0,0,0,0],"vertices":{"rawPosition":[-275,-450,0,275,-450,0,-275,450,0,275,450,0],"indexes":[0,1,2,2,1,3],"uv":[0,900,550,900,0,0,550,0],"nuv":[0,0,1,0,0,1,1,1],"minPos":{"x":-275,"y":-450,"z":0},"maxPos":{"x":275,"y":450,"z":0}},"packable":true,"pixelsToUnit":100,"pivot":{"x":0.5,"y":0.5},"meshType":0}],[0],0,[0],[0],[1]],[[{"name":"2","rect":{"x":0,"y":0,"width":550,"height":900},"offset":{"x":0,"y":0},"originalSize":{"width":550,"height":900},"rotated":false,"capInsets":[0,0,0,0],"vertices":{"rawPosition":[-275,-450,0,275,-450,0,-275,450,0,275,450,0],"indexes":[0,1,2,2,1,3],"uv":[0,900,550,900,0,0,550,0],"nuv":[0,0,1,0,0,1,1,1],"minPos":{"x":-275,"y":-450,"z":0},"maxPos":{"x":275,"y":450,"z":0}},"packable":true,"pixelsToUnit":100,"pivot":{"x":0.5,"y":0.5},"meshType":0}],[0],0,[0],[0],[2]],[[{"name":"14","rect":{"x":0,"y":0,"width":550,"height":900},"offset":{"x":0,"y":0},"originalSize":{"width":550,"height":900},"rotated":false,"capInsets":[0,0,0,0],"vertices":{"rawPosition":[-275,-450,0,275,-450,0,-275,450,0,275,450,0],"indexes":[0,1,2,2,1,3],"uv":[0,900,550,900,0,0,550,0],"nuv":[0,0,1,0,0,1,1,1],"minPos":{"x":-275,"y":-450,"z":0},"maxPos":{"x":275,"y":450,"z":0}},"packable":true,"pixelsToUnit":100,"pivot":{"x":0.5,"y":0.5},"meshType":0}],[0],0,[0],[0],[3]],[[{"name":"0","rect":{"x":0,"y":0,"width":550,"height":900},"offset":{"x":0,"y":0},"originalSize":{"width":550,"height":900},"rotated":false,"capInsets":[0,0,0,0],"vertices":{"rawPosition":[-275,-450,0,275,-450,0,-275,450,0,275,450,0],"indexes":[0,1,2,2,1,3],"uv":[0,900,550,900,0,0,550,0],"nuv":[0,0,1,0,0,1,1,1],"minPos":{"x":-275,"y":-450,"z":0},"maxPos":{"x":275,"y":450,"z":0}},"packable":true,"pixelsToUnit":100,"pivot":{"x":0.5,"y":0.5},"meshType":0}],[0],0,[0],[0],[4]],[[{"name":"12","rect":{"x":0,"y":0,"width":550,"height":900},"offset":{"x":0,"y":0},"originalSize":{"width":550,"height":900},"rotated":false,"capInsets":[0,0,0,0],"vertices":{"rawPosition":[-275,-450,0,275,-450,0,-275,450,0,275,450,0],"indexes":[0,1,2,2,1,3],"uv":[0,900,550,900,0,0,550,0],"nuv":[0,0,1,0,0,1,1,1],"minPos":{"x":-275,"y":-450,"z":0},"maxPos":{"x":275,"y":450,"z":0}},"packable":true,"pixelsToUnit":100,"pivot":{"x":0.5,"y":0.5},"meshType":0}],[0],0,[0],[0],[5]],[[{"name":"5","rect":{"x":0,"y":0,"width":550,"height":900},"offset":{"x":0,"y":0},"originalSize":{"width":550,"height":900},"rotated":false,"capInsets":[0,0,0,0],"vertices":{"rawPosition":[-275,-450,0,275,-450,0,-275,450,0,275,450,0],"indexes":[0,1,2,2,1,3],"uv":[0,900,550,900,0,0,550,0],"nuv":[0,0,1,0,0,1,1,1],"minPos":{"x":-275,"y":-450,"z":0},"maxPos":{"x":275,"y":450,"z":0}},"packable":true,"pixelsToUnit":100,"pivot":{"x":0.5,"y":0.5},"meshType":0}],[0],0,[0],[0],[6]],[[{"name":"8","rect":{"x":0,"y":0,"width":550,"height":900},"offset":{"x":0,"y":0},"originalSize":{"width":550,"height":900},"rotated":false,"capInsets":[0,0,0,0],"vertices":{"rawPosition":[-275,-450,0,275,-450,0,-275,450,0,275,450,0],"indexes":[0,1,2,2,1,3],"uv":[0,900,550,900,0,0,550,0],"nuv":[0,0,1,0,0,1,1,1],"minPos":{"x":-275,"y":-450,"z":0},"maxPos":{"x":275,"y":450,"z":0}},"packable":true,"pixelsToUnit":100,"pivot":{"x":0.5,"y":0.5},"meshType":0}],[0],0,[0],[0],[7]],[[{"name":"10","rect":{"x":0,"y":0,"width":550,"height":900},"offset":{"x":0,"y":0},"originalSize":{"width":550,"height":900},"rotated":false,"capInsets":[0,0,0,0],"vertices":{"rawPosition":[-275,-450,0,275,-450,0,-275,450,0,275,450,0],"indexes":[0,1,2,2,1,3],"uv":[0,900,550,900,0,0,550,0],"nuv":[0,0,1,0,0,1,1,1],"minPos":{"x":-275,"y":-450,"z":0},"maxPos":{"x":275,"y":450,"z":0}},"packable":true,"pixelsToUnit":100,"pivot":{"x":0.5,"y":0.5},"meshType":0}],[0],0,[0],[0],[8]],[[{"name":"6","rect":{"x":0,"y":0,"width":550,"height":900},"offset":{"x":0,"y":0},"originalSize":{"width":550,"height":900},"rotated":false,"capInsets":[0,0,0,0],"vertices":{"rawPosition":[-275,-450,0,275,-450,0,-275,450,0,275,450,0],"indexes":[0,1,2,2,1,3],"uv":[0,900,550,900,0,0,550,0],"nuv":[0,0,1,0,0,1,1,1],"minPos":{"x":-275,"y":-450,"z":0},"maxPos":{"x":275,"y":450,"z":0}},"packable":true,"pixelsToUnit":100,"pivot":{"x":0.5,"y":0.5},"meshType":0}],[0],0,[0],[0],[9]],[[{"name":"11","rect":{"x":0,"y":0,"width":550,"height":900},"offset":{"x":0,"y":0},"originalSize":{"width":550,"height":900},"rotated":false,"capInsets":[0,0,0,0],"vertices":{"rawPosition":[-275,-450,0,275,-450,0,-275,450,0,275,450,0],"indexes":[0,1,2,2,1,3],"uv":[0,900,550,900,0,0,550,0],"nuv":[0,0,1,0,0,1,1,1],"minPos":{"x":-275,"y":-450,"z":0},"maxPos":{"x":275,"y":450,"z":0}},"packable":true,"pixelsToUnit":100,"pivot":{"x":0.5,"y":0.5},"meshType":0}],[0],0,[0],[0],[10]],[[{"name":"1","rect":{"x":0,"y":0,"width":550,"height":900},"offset":{"x":0,"y":0},"originalSize":{"width":550,"height":900},"rotated":false,"capInsets":[0,0,0,0],"vertices":{"rawPosition":[-275,-450,0,275,-450,0,-275,450,0,275,450,0],"indexes":[0,1,2,2,1,3],"uv":[0,900,550,900,0,0,550,0],"nuv":[0,0,1,0,0,1,1,1],"minPos":{"x":-275,"y":-450,"z":0},"maxPos":{"x":275,"y":450,"z":0}},"packable":true,"pixelsToUnit":100,"pivot":{"x":0.5,"y":0.5},"meshType":0}],[0],0,[0],[0],[11]],[[{"name":"7","rect":{"x":0,"y":0,"width":550,"height":900},"offset":{"x":0,"y":0},"originalSize":{"width":550,"height":900},"rotated":false,"capInsets":[0,0,0,0],"vertices":{"rawPosition":[-275,-450,0,275,-450,0,-275,450,0,275,450,0],"indexes":[0,1,2,2,1,3],"uv":[0,900,550,900,0,0,550,0],"nuv":[0,0,1,0,0,1,1,1],"minPos":{"x":-275,"y":-450,"z":0},"maxPos":{"x":275,"y":450,"z":0}},"packable":true,"pixelsToUnit":100,"pivot":{"x":0.5,"y":0.5},"meshType":0}],[0],0,[0],[0],[12]],[[{"name":"9","rect":{"x":0,"y":0,"width":550,"height":900},"offset":{"x":0,"y":0},"originalSize":{"width":550,"height":900},"rotated":false,"capInsets":[0,0,0,0],"vertices":{"rawPosition":[-275,-450,0,275,-450,0,-275,450,0,275,450,0],"indexes":[0,1,2,2,1,3],"uv":[0,900,550,900,0,0,550,0],"nuv":[0,0,1,0,0,1,1,1],"minPos":{"x":-275,"y":-450,"z":0},"maxPos":{"x":275,"y":450,"z":0}},"packable":true,"pixelsToUnit":100,"pivot":{"x":0.5,"y":0.5},"meshType":0}],[0],0,[0],[0],[13]],[[{"name":"13","rect":{"x":0,"y":0,"width":550,"height":900},"offset":{"x":0,"y":0},"originalSize":{"width":550,"height":900},"rotated":false,"capInsets":[0,0,0,0],"vertices":{"rawPosition":[-275,-450,0,275,-450,0,-275,450,0,275,450,0],"indexes":[0,1,2,2,1,3],"uv":[0,900,550,900,0,0,550,0],"nuv":[0,0,1,0,0,1,1,1],"minPos":{"x":-275,"y":-450,"z":0},"maxPos":{"x":275,"y":450,"z":0}},"packable":true,"pixelsToUnit":100,"pivot":{"x":0.5,"y":0.5},"meshType":0}],[0],0,[0],[0],[14]]]]
